LICENSE
MANIFEST.in
README.md
setup.py
django_singleactiveobject.egg-info/PKG-INFO
django_singleactiveobject.egg-info/SOURCES.txt
django_singleactiveobject.egg-info/dependency_links.txt
django_singleactiveobject.egg-info/requires.txt
django_singleactiveobject.egg-info/top_level.txt
singleactiveobject/__init__.py
singleactiveobject/models.py
singleactiveobject/tests/__init__.py
singleactiveobject/tests/models.py
singleactiveobject/tests/models_tests.py
singleactiveobject/tests/runtests.py