Metadata-Version: 1.0
Name: django-singleactiveobject
Version: 0.9.1
Summary: Model mixin that ensures there is only one active model instance in your database.
Home-page: https://github.com/byteweaver/django-singleactiveobject
Author: byteweaver
Author-email: contact@byteweaver.net
License: Copyright (c) 2012, byteweaver
